zinnia_markitup/__init__.py
zinnia_markitup/admin.py
zinnia_markitup/tests.py
zinnia_markitup/static/zinnia_markitup/js/jquery.min.js
zinnia_markitup/static/zinnia_markitup/js/markitup/jquery.markitup.js
zinnia_markitup/static/zinnia_markitup/js/markitup/sets/html/set.js
zinnia_markitup/static/zinnia_markitup/js/markitup/sets/html/style.css
zinnia_markitup/static/zinnia_markitup/js/markitup/sets/html/images/bold.png
zinnia_markitup/static/zinnia_markitup/js/markitup/sets/html/images/clean.png
zinnia_markitup/static/zinnia_markitup/js/markitup/sets/html/images/h1.png
zinnia_markitup/static/zinnia_markitup/js/markitup/sets/html/images/h2.png
zinnia_markitup/static/zinnia_markitup/js/markitup/sets/html/images/h3.png
zinnia_markitup/static/zinnia_markitup/js/markitup/sets/html/images/h4.png
zinnia_markitup/static/zinnia_markitup/js/markitup/sets/html/images/h5.png
zinnia_markitup/static/zinnia_markitup/js/markitup/sets/html/images/h6.png
zinnia_markitup/static/zinnia_markitup/js/markitup/sets/html/images/image.png
zinnia_markitup/static/zinnia_markitup/js/markitup/sets/html/images/italic.png
zinnia_markitup/static/zinnia_markitup/js/markitup/sets/html/images/link.png
zinnia_markitup/static/zinnia_markitup/js/markitup/sets/html/images/list-bullet.png
zinnia_markitup/static/zinnia_markitup/js/markitup/sets/html/images/list-item.png
zinnia_markitup/static/zinnia_markitup/js/markitup/sets/html/images/list-numeric.png
zinnia_markitup/static/zinnia_markitup/js/markitup/sets/html/images/paragraph.png
zinnia_markitup/static/zinnia_markitup/js/markitup/sets/html/images/picture.png
zinnia_markitup/static/zinnia_markitup/js/markitup/sets/html/images/preview.png
zinnia_markitup/static/zinnia_markitup/js/markitup/sets/html/images/stroke.png
zinnia_markitup/static/zinnia_markitup/js/markitup/sets/markdown/set.js
zinnia_markitup/static/zinnia_markitup/js/markitup/sets/markdown/style.css
zinnia_wysiwyg_markitup-1.2.dist-info/DESCRIPTION.rst
zinnia_wysiwyg_markitup-1.2.dist-info/METADATA
zinnia_wysiwyg_markitup-1.2.dist-info/RECORD
zinnia_wysiwyg_markitup-1.2.dist-info/WHEEL
zinnia_wysiwyg_markitup-1.2.dist-info/metadata.json
zinnia_wysiwyg_markitup-1.2.dist-info/top_level.txt
